grupob_zoho/__init__.py
grupob_zoho/zoho.py
grupob_zoho-0.1.1.dist-info/LICENCE
grupob_zoho-0.1.1.dist-info/METADATA
grupob_zoho-0.1.1.dist-info/WHEEL
grupob_zoho-0.1.1.dist-info/top_level.txt
grupob_zoho-0.1.1.dist-info/RECORD
