Metadata-Version: 2.1
Name: grupob_zoho
Version: 0.1.1
Summary: Uma biblioteca para manipular dados no zoho
Home-page: https://github.com/juniorppp/zoho
Author: Gelson Júnior
Author-email: gelson.junior@grupobachega.com.br
Classifier: Programming Language :: Python :: 3
Classifier: License :: OSI Approved :: MIT License
Classifier: Operating System :: OS Independent
Requires-Python: >=3.6
License-File: LICENCE
Requires-Dist: requests
